dictionary_parser/__init__.py
dictionary_parser/__main__.py
dictionary_parser/core/__init__.py
dictionary_parser/core/processor.py
dictionary_parser/main.py
dictionary_parser/utils/__init__.py
dictionary_parser/utils/case.py
dictionary_parser/utils/letters.py
dictionary_parser/utils/validations.py
dictionary_parser-0.3.0.dist-info/LICENSE
dictionary_parser-0.3.0.dist-info/METADATA
dictionary_parser-0.3.0.dist-info/WHEEL
dictionary_parser-0.3.0.dist-info/entry_points.txt
dictionary_parser-0.3.0.dist-info/RECORD
