Metadata-Version: 2.3
Name: dictionary-parser
Version: 0.3.0
Summary: A CLI tool for generating csv or json files from word dictionaries.
License: MIT
Author: The Casual Dev
Author-email: thecasualdev@gmail.com
Requires-Python: >=3.9,<4.0
Classifier: License :: OSI Approved :: MIT License
Classifier: Programming Language :: Python :: 3
Classifier: Programming Language :: Python :: 3.9
Classifier: Programming Language :: Python :: 3.10
Classifier: Programming Language :: Python :: 3.11
Classifier: Programming Language :: Python :: 3.12
Classifier: Programming Language :: Python :: 3.13
Requires-Dist: requests
Requires-Dist: typer[all]
